.VERSION
AUTHORS.rst
CONTRIBUTING.rst
HISTORY.rst
LICENSE
MANIFEST.in
Pipfile
Pipfile.lock
README.rst
USAGE.rst
dev-requirements.txt
requirements.txt
setup.cfg
setup.py
awsssolib/.VERSION
awsssolib/AUTHORS.rst
awsssolib/CONTRIBUTING.rst
awsssolib/HISTORY.rst
awsssolib/LICENSE
awsssolib/Pipfile
awsssolib/Pipfile.lock
awsssolib/README.rst
awsssolib/USAGE.rst
awsssolib/__init__.py
awsssolib/_version.py
awsssolib/awsssolib.py
awsssolib/awsssolibexceptions.py
awsssolib/dev-requirements.txt
awsssolib/requirements.txt
awsssolib.egg-info/PKG-INFO
awsssolib.egg-info/SOURCES.txt
awsssolib.egg-info/dependency_links.txt
awsssolib.egg-info/not-zip-safe
awsssolib.egg-info/requires.txt
awsssolib.egg-info/top_level.txt
awsssolib/__pycache__/__init__.cpython-37.pyc
awsssolib/__pycache__/_version.cpython-37.pyc
awsssolib/__pycache__/awsssolib.cpython-37.pyc
awsssolib/__pycache__/awsssolibexceptions.cpython-37.pyc
awsssolib/__pycache__/configuration.cpython-37.pyc
awsssolib/__pycache__/utils.cpython-37.pyc
awsssolib/entities/__init__.py
awsssolib/entities/entities.py
awsssolib/entities/__pycache__/__init__.cpython-37.pyc
awsssolib/entities/__pycache__/core.cpython-37.pyc
awsssolib/entities/__pycache__/entities.cpython-37.pyc
docs/Makefile
docs/authors.rst
docs/conf.py
docs/contributing.rst
docs/history.rst
docs/index.rst
docs/installation.rst
docs/readme.rst
docs/usage.rst