Metadata-Version: 1.1
Name: awsssolib
Version: 0.1.2
Summary: A template to create python libraries
Home-page: https://enx.gitlab.schubergphilis.com/python/awsssolib
Author: Sayantan Khanra
Author-email: skhanra@schubergphilis.com
License: MIT
Keywords: awsssolib
Platform: UNKNOWN
Classifier: Development Status :: 1 - Planning
Classifier: Intended Audience :: Developers
Classifier: License :: OSI Approved :: MIT License
Classifier: Natural Language :: English
Classifier: Programming Language :: Python :: 3.7
